ntm/__init__.py
ntm/old_files/__init__.py
ntm/old_files/collect.py
ntm/old_files/import.py
ntm/old_files/read.py
ntm/old_files/translate.py
ntm-0.1.1.dist-info/METADATA
ntm-0.1.1.dist-info/WHEEL
ntm-0.1.1.dist-info/licence.txt
ntm-0.1.1.dist-info/top_level.txt
ntm-0.1.1.dist-info/RECORD
