Metadata-Version: 2.1
Name: ntm
Version: 0.1.1
Summary: Neural Topic Modelling
Home-page: https://github.com/pamelahathway/neural_topic_modelling
Author: Pamela Hathway, Dan Goodman
Author-email: d.goodman@imperial.ac.uk
License: UNKNOWN
Project-URL: Bug Tracker, https://github.com/pamelahathway/neural_topic_modelling/issues
Platform: UNKNOWN
Classifier: Programming Language :: Python :: 3
Classifier: License :: OSI Approved :: MIT License
Classifier: Operating System :: OS Independent
Classifier: Development Status :: 3 - Alpha
Classifier: Intended Audience :: Science/Research
Classifier: Natural Language :: English
Classifier: Topic :: Scientific/Engineering :: Artificial Intelligence
Classifier: Topic :: Scientific/Engineering :: Bio-Informatics
Requires-Python: >=3.7
